{
  "version": "7",
  "dialect": "postgresql",
  "entries": [
    {
      "idx": 0,
      "version": "7",
      "when": 1777269111821,
      "tag": "0000_swift_charles_xavier",
      "breakpoints": true
    },
    {
      "idx": 1,
      "version": "7",
      "when": 1777387491357,
      "tag": "0001_ambiguous_hercules",
      "breakpoints": true
    },
    {
      "idx": 2,
      "version": "7",
      "when": 1782362822941,
      "tag": "0002_fixed_terrax",
      "breakpoints": true
    },
    {
      "idx": 3,
      "version": "7",
      "when": 1782375010383,
      "tag": "0003_soft_human_fly",
      "breakpoints": true
    },
    {
      "idx": 4,
      "version": "7",
      "when": 1782556329259,
      "tag": "0004_powerful_orphan",
      "breakpoints": true
    },
    {
      "idx": 5,
      "version": "7",
      "when": 1782580795665,
      "tag": "0005_shiny_psylocke",
      "breakpoints": true
    },
    {
      "idx": 6,
      "version": "7",
      "when": 1782592626149,
      "tag": "0006_giant_pandemic",
      "breakpoints": true
    },
    {
      "idx": 7,
      "version": "7",
      "when": 1782619481225,
      "tag": "0007_regular_stryfe",
      "breakpoints": true
    },
    {
      "idx": 8,
      "version": "7",
      "when": 1782627887952,
      "tag": "0008_clumsy_susan_delgado",
      "breakpoints": true
    },
    {
      "idx": 9,
      "version": "7",
      "when": 1782666921285,
      "tag": "0009_gray_kree",
      "breakpoints": true
    },
    {
      "idx": 10,
      "version": "7",
      "when": 1782666921286,
      "tag": "0010_fix_csm_cases_requester_ondelete",
      "breakpoints": true
    },
    {
      "idx": 11,
      "version": "7",
      "when": 1782742305343,
      "tag": "0011_sticky_norman_osborn",
      "breakpoints": true
    },
    {
      "idx": 12,
      "version": "7",
      "when": 1782784692964,
      "tag": "0012_slow_ronan",
      "breakpoints": true
    },
    {
      "idx": 13,
      "version": "7",
      "when": 1783049839359,
      "tag": "0013_living_sir_ram",
      "breakpoints": true
    },
    {
      "idx": 14,
      "version": "7",
      "when": 1783050225088,
      "tag": "0014_bright_talkback",
      "breakpoints": true
    }
  ]
}